LICENSE
README.md
setup.py
rock_avatars/__init__.py
rock_avatars/avatar.py
rock_avatars/avatar_instance.py
rock_avatars/consumer.py
rock_avatars/index.py
rock_avatars/log.py
rock_avatars/oss.py
rock_avatars/psd_compose.py
rock_avatars/unit.py
rock_avatars/unit_group.py
rock_avatars/unit_info.py
rock_avatars/version.py
rock_avatars.egg-info/PKG-INFO
rock_avatars.egg-info/SOURCES.txt
rock_avatars.egg-info/dependency_links.txt
rock_avatars.egg-info/requires.txt
rock_avatars.egg-info/top_level.txt