Metadata-Version: 2.1
Name: rock-avatars
Version: 0.0.2
Summary: Rockflow Avatars generator
Home-page: https://github.com/day253/rock-avatars
Author: Junkai Dai
Author-email: daijunkai@flowcapai.com
License: UNKNOWN
Platform: any
Provides-Extra: develop
License-File: LICENSE
